{
	"statTotal": 4,
	"abilityUpgradeMax": 7,
	"statUpgradeMax": 7,
	"characters": [
		{
			"id":					1,
			"name":					"Zoey",
			"type":					"player",
			"age":					12,
			"homePlanet":			"Verdura",
			"currentHp":			14,
			"totalHp":				14,
			"ap":					5,
			"attack":				3,
			"stats": {
				"strength":			1,
				"speed":			1,
				"sway":				-1,
				"sneak":			1,
				"intelligence":		2,
				"perception":		0
			},
			"backstory":			"Loyal warrior from Earth.",
			"abilityUpgradePoints":	0,
			"statUpgradePoints":	0,
			"tags":					[]
		},
		{
			"id":					2,
			"name":					"Luna",
			"type":					"player",
			"age":					12,
			"homePlanet":			"Verdura",
			"currentHp":			14,
			"totalHp":				14,
			"ap":					5,
			"attack":				3,
			"stats": {
				"strength":			5,
				"speed":			7,
				"sway":				4,
				"sneak":			3,
				"intelligence":		8,
				"perception":		6
			},
			"backstory":			"Loyal warrior from Earth.",
			"abilityUpgradePoints":	0,
			"statUpgradePoints":	0,
			"tags":					[]
		},
		{
			"id":					3,
			"name":					"Kaz",
			"type":					"NPC",
			"age":					12,
			"homePlanet":			"Land of the Hearth",
			"currentHp":			14,
			"totalHp":				14,
			"ap":					5,
			"attack":				3,
			"stats": {
				"strength":			5,
				"speed":			7,
				"sway":				4,
				"sneak":			3,
				"intelligence":		8,
				"perception":		6
			},
			"backstory":			"Loyal warrior from Earth.",
			"abilityUpgradePoints":	0,
			"statUpgradePoints":	0,
			"tags":					[]
		},
		{
			"id":					4,
			"name":					"Picard",
			"type":					"NPC",
			"age":					12,
			"homePlanet":			"Earth",
			"currentHp":			14,
			"totalHp":				14,
			"ap":					5,
			"attack":				3,
			"stats": {
				"strength":			5,
				"speed":			7,
				"sway":				4,
				"sneak":			3,
				"intelligence":		8,
				"perception":		6
			},
			"backstory":			"Loyal warrior from Earth.",
			"abilityUpgradePoints":	0,
			"statUpgradePoints":	0,
			"tags":					["Starfleet"]
		}
	]
}